yagdrive/__init__.py
yagdrive/auth.py
yagdrive/core.py
yagdrive-1.4.1.dist-info/LICENSE
yagdrive-1.4.1.dist-info/METADATA
yagdrive-1.4.1.dist-info/WHEEL
yagdrive-1.4.1.dist-info/top_level.txt
yagdrive-1.4.1.dist-info/RECORD
