Metadata-Version: 2.1
Name: yagdrive
Version: 1.4.1
Summary: Yet Another Google Drive API Python wrapper
Home-page: https://github.com/sdelquin/yagdrive.git
Author: Sergio Delgado Quintero
Author-email: sdelquin@gmail.com
License: MIT
Platform: UNKNOWN
Requires-Python: >=3.6
Requires-Dist: pydrive (>=1.3.1)
Requires-Dist: mimetype-description (>=0.0.6)
